pyesbulk/__init__.py
pyesbulk-2.1.1.dist-info/LICENSE
pyesbulk-2.1.1.dist-info/METADATA
pyesbulk-2.1.1.dist-info/WHEEL
pyesbulk-2.1.1.dist-info/top_level.txt
pyesbulk-2.1.1.dist-info/RECORD
